hydrocluster/__init__.py
hydrocluster/hydrocluster.py
hydrocluster/core/__init__.py
hydrocluster/core/pdbcluster.py
hydrocluster/core/s_dbw.py
hydrocluster/dbcreator/__init__.py
hydrocluster/dbcreator/testlist.py
hydrocluster/ui/__init__.py
hydrocluster/ui/cli.py
hydrocluster/ui/tkgui.py
hydrocluster-0.2.0.dist-info/LICENSE
hydrocluster-0.2.0.dist-info/METADATA
hydrocluster-0.2.0.dist-info/WHEEL
hydrocluster-0.2.0.dist-info/entry_points.txt
hydrocluster-0.2.0.dist-info/top_level.txt
hydrocluster-0.2.0.dist-info/RECORD
