Metadata-Version: 2.1
Name: hydrocluster
Version: 0.2.0
Summary: Cluster analysis of hydrophobic or charged regions of macromolecules. The program is based on the DBSCAN algorithm.
Home-page: https://github.com/alashkov83/hydrocluster
Author: Alexander Lashkov, Sergey Rubinsky, Polina Eistrikh-Heller
Author-email: alashkov83@gmail.com
Maintainer: Alexander Lashkov
License: GPL v.3
Keywords: molecular modeling,bioinformatic,protein structure,hydrophobic core,hydrophobic cluster,DBSCAN
Platform: any
Classifier: Development Status :: 1 - Planning
Classifier: Environment :: Console
Classifier: Environment :: Win32 (MS Windows)
Classifier: Environment :: X11 Applications
Classifier: Intended Audience :: Science/Research
Classifier: Intended Audience :: Education
Classifier: License :: OSI Approved :: GNU General Public License v3 (GPLv3)
Classifier: Natural Language :: English
Classifier: Operating System :: OS Independent
Classifier: Programming Language :: Python :: 3 :: Only
Classifier: Programming Language :: Python :: 3.4
Classifier: Programming Language :: Python :: 3.5
Classifier: Programming Language :: Python :: 3.6
Classifier: Programming Language :: Python :: 3.7
Classifier: Programming Language :: Python :: Implementation :: CPython
Classifier: Topic :: Scientific/Engineering :: Bio-Informatics
Requires-Python: >=3.4
Requires-Dist: hjson
Requires-Dist: psutil
Requires-Dist: scipy
Requires-Dist: progressbar2
Requires-Dist: matplotlib (>=1.5.1)
Requires-Dist: numpy (>=1.14.2)
Requires-Dist: scikit-learn (>=0.18.0)
Requires-Dist: biopython (>=1.71)
Requires-Dist: mmtf-python (>=1.1.0)
Requires-Dist: msgpack (>=0.5.6)
